bestpkg/__init__.py
bestpkg_001-0.0.1.dist-info/LICENCE
bestpkg_001-0.0.1.dist-info/METADATA
bestpkg_001-0.0.1.dist-info/WHEEL
bestpkg_001-0.0.1.dist-info/top_level.txt
bestpkg_001-0.0.1.dist-info/RECORD
