Metadata-Version: 2.1
Name: bestpkg-001
Version: 0.0.1
Summary: 一个牛逼的程序
Home-page: UNKNOWN
Author: Zhong Lei
Author-email: 625015751@qq.com
License: UNKNOWN
Platform: UNKNOWN
Classifier: Programming Language :: Python :: 3
Classifier: License :: OSI Approved :: GNU Lesser General Public License v3 or later (LGPLv3+)
Classifier: Operating System :: OS Independent
